COPYING
MANIFEST.in
README.rst
bootstrap.py
buildout.cfg
setup.py
docs/conf.py
docs/index.rst
xbob/__init__.py
xbob.db.biosecurid.face.egg-info/PKG-INFO
xbob.db.biosecurid.face.egg-info/SOURCES.txt
xbob.db.biosecurid.face.egg-info/dependency_links.txt
xbob.db.biosecurid.face.egg-info/entry_points.txt
xbob.db.biosecurid.face.egg-info/namespace_packages.txt
xbob.db.biosecurid.face.egg-info/not-zip-safe
xbob.db.biosecurid.face.egg-info/requires.txt
xbob.db.biosecurid.face.egg-info/top_level.txt
xbob/db/__init__.py
xbob/db/biosecurid/__init__.py
xbob/db/biosecurid/face/__init__.py
xbob/db/biosecurid/face/create.py
xbob/db/biosecurid/face/db.sql3
xbob/db/biosecurid/face/driver.py
xbob/db/biosecurid/face/models.py
xbob/db/biosecurid/face/query.py
xbob/db/biosecurid/face/test.py