Metadata-Version: 1.1
Name: xbob.db.biosecurid.face
Version: 0.0.1a0
Summary: BiosecurID Database Access API for Bob
Home-page: https://pypi.python.org/pypi/xbob.db.biosecurid.face
Author: UNKNOWN
Author-email: UNKNOWN
License: GPLv3
Keywords: face recognition,bob,xbob,xbob.db
Platform: UNKNOWN
Classifier: Development Status :: 3 - Alpha
Classifier: Environment :: Console
Classifier: Intended Audience :: Developers
Classifier: Intended Audience :: Education
Classifier: Intended Audience :: Science/Research
Classifier: License :: OSI Approved :: GNU General Public License v3 (GPLv3)
Classifier: Natural Language :: English
Classifier: Programming Language :: Python
Classifier: Programming Language :: Python :: 3
Classifier: Topic :: Scientific/Engineering :: Artificial Intelligence
Classifier: Topic :: Database :: Front-Ends
